{
    "chartBody": {
        "title": "振荡波-局放-放电次数图谱(现场数据V0.2)",
        "axisInfo": {
            "xDesc": "位置",
            "yDesc": "放电次数",
            "nameLocation": "middle",
            "yUnit": "",
            "xRangeMin": 0,
            "xRangeMax": 2310,
            "xUnit": "m"
        },
        "series": [
            {
                "color": "rgba(255, 150, 47,1)",
                "dataList": [
                    [
                        1432,
                        1
                    ],
                    [
                        688,
                        1
                    ],
                    [
                        1524,
                        1
                    ],
                    [
                        351,
                        1
                    ]
                ],
                "name": "L1"
            },
            {
                "color": "rgba(0, 255, 27,1)",
                "dataList": [
                    [
                        1674,
                        1
                    ],
                    [
                        970,
                        1
                    ],
                    [
                        1187,
                        1
                    ],
                    [
                        305,
                        1
                    ],
                    [
                        1377,
                        1
                    ],
                    [
                        1126,
                        1
                    ],
                    [
                        888,
                        1
                    ],
                    [
                        1658,
                        1
                    ]
                ],
                "name": "L2"
            },
            {
                "color": "rgba(255, 20, 10,1)",
                "dataList": [
                    [
                        578,
                        1
                    ],
                    [
                        1540,
                        1
                    ],
                    [
                        1817,
                        1
                    ],
                    [
                        1701,
                        1
                    ],
                    [
                        196,
                        1
                    ],
                    [
                        426,
                        1
                    ],
                    [
                        427,
                        1
                    ],
                    [
                        1340,
                        1
                    ],
                    [
                        1350,
                        1
                    ],
                    [
                        760,
                        1
                    ],
                    [
                        1655,
                        1
                    ]
                ],
                "name": "L3"
            }
        ],
        "trigger": null
    },
    "isAccumulated": null,
    "spectrumType": 162
}